pyhider/__init__.py
pyhider/main.py
pyhider-1.7.dist-info/METADATA
pyhider-1.7.dist-info/WHEEL
pyhider-1.7.dist-info/entry_points.txt
pyhider-1.7.dist-info/top_level.txt
pyhider-1.7.dist-info/RECORD
