Metadata-Version: 2.4
Name: pyhider
Version: 1.7
Summary: Python obfuscation and compiling tool
Author: Kalom
Author-email: 
Requires-Python: >=3.6
